solun/__init__.py
solun/main.py
solun-0.0.5.dist-info/METADATA
solun-0.0.5.dist-info/WHEEL
solun-0.0.5.dist-info/entry_points.txt
solun-0.0.5.dist-info/top_level.txt
solun-0.0.5.dist-info/zip-safe
solun-0.0.5.dist-info/RECORD
