Metadata-Version: 2.1
Name: solun
Version: 0.0.5
Summary: Solun-CLI is a command line interface tool for uploading files to Solun.
Home-page: https://solun.pm/
Author: Daniel Wagner
Author-email: contact@solun.pm
License: MIT
Keywords: CLI,file-upload,solun,solun-cli,solun-pm
Classifier: Programming Language :: Python :: 3
Classifier: License :: OSI Approved :: MIT License
Classifier: Operating System :: OS Independent
Requires-Dist: httpx ==0.25.1
Requires-Dist: python-bcrypt ==0.3.2
Requires-Dist: tqdm ==4.66.1
